odoo/addons/l10n_es_aeat_mod390/README.rst
odoo/addons/l10n_es_aeat_mod390/__init__.py
odoo/addons/l10n_es_aeat_mod390/__manifest__.py
odoo/addons/l10n_es_aeat_mod390/data/aeat_export_mod390_2019_sub04_data.xml
odoo/addons/l10n_es_aeat_mod390/data/aeat_export_mod390_2019_sub07_data.xml
odoo/addons/l10n_es_aeat_mod390/data/aeat_export_mod390_2019_sub08_data.xml
odoo/addons/l10n_es_aeat_mod390/data/l10n.es.aeat.map.tax.csv
odoo/addons/l10n_es_aeat_mod390/data/l10n.es.aeat.map.tax.line.account.csv
odoo/addons/l10n_es_aeat_mod390/data/l10n.es.aeat.map.tax.line.csv
odoo/addons/l10n_es_aeat_mod390/data/l10n.es.aeat.map.tax.line.tax.csv
odoo/addons/l10n_es_aeat_mod390/data/2021/aeat.model.export.config.csv
odoo/addons/l10n_es_aeat_mod390/data/2021/aeat.model.export.config.line.csv
odoo/addons/l10n_es_aeat_mod390/data/2022/aeat.model.export.config.csv
odoo/addons/l10n_es_aeat_mod390/data/2022/aeat.model.export.config.line.csv
odoo/addons/l10n_es_aeat_mod390/data/2023/aeat.model.export.config.csv
odoo/addons/l10n_es_aeat_mod390/data/2023/aeat.model.export.config.line.csv
odoo/addons/l10n_es_aeat_mod390/data/2024/aeat.model.export.config.csv
odoo/addons/l10n_es_aeat_mod390/data/2024/aeat.model.export.config.line.csv
odoo/addons/l10n_es_aeat_mod390/data/2024/l10n.es.aeat.map.tax.csv
odoo/addons/l10n_es_aeat_mod390/data/2024/l10n.es.aeat.map.tax.line.csv
odoo/addons/l10n_es_aeat_mod390/data/2024/l10n.es.aeat.map.tax.line.tax.csv
odoo/addons/l10n_es_aeat_mod390/data/2025/aeat.model.export.config.csv
odoo/addons/l10n_es_aeat_mod390/data/2025/aeat.model.export.config.line.csv
odoo/addons/l10n_es_aeat_mod390/docs/dr390e2022.xlsx
odoo/addons/l10n_es_aeat_mod390/docs/dr390e2024.xlsx
odoo/addons/l10n_es_aeat_mod390/docs/instr390.pdf
odoo/addons/l10n_es_aeat_mod390/i18n/ca.po
odoo/addons/l10n_es_aeat_mod390/i18n/es.po
odoo/addons/l10n_es_aeat_mod390/i18n/l10n_es_aeat_mod390.pot
odoo/addons/l10n_es_aeat_mod390/models/__init__.py
odoo/addons/l10n_es_aeat_mod390/models/account_move.py
odoo_addon_l10n_es_aeat_mod390-18.0.1.1.1.dist-info/METADATA
odoo_addon_l10n_es_aeat_mod390-18.0.1.1.1.dist-info/WHEEL
odoo_addon_l10n_es_aeat_mod390-18.0.1.1.1.dist-info/top_level.txt
odoo_addon_l10n_es_aeat_mod390-18.0.1.1.1.dist-info/RECORD
